{"history":{"2024-02-24":{"words":1555,"characters":3011,"sentences":0,"pages":5,"files":8,"footnotes":0,"citations":0,"totalWords":3071,"totalCharacters":6117,"totalSentences":13,"totalFootnotes":0,"totalCitations":0,"totalPages":10.2},"2024-02-25":{"words":673,"characters":1276,"sentences":0,"pages":2.2,"files":8,"footnotes":0,"citations":0,"totalWords":3744,"totalCharacters":7396,"totalSentences":13,"totalFootnotes":0,"totalCitations":0,"totalPages":12.400000000000002}},"modifiedFiles":{"100-UTTU人物合辑/神秘学家｜Arcanist/十四行诗.md":{"words":{"initial":1079,"current":1723},"characters":{"initial":2008,"current":2997},"sentences":{"initial":1,"current":1},"footnotes":{"initial":0,"current":0},"citations":{"initial":0,"current":0},"pages":{"initial":3.6,"current":5.7}},"300-箱外世界/暴雨时间线.md":{"words":{"initial":772,"current":772},"characters":{"initial":1366,"current":1365},"sentences":{"initial":1,"current":1},"footnotes":{"initial":0,"current":0},"citations":{"initial":0,"current":0},"pages":{"initial":2.6,"current":2.6}},"000-箱的构成/templates/UTTU人物合辑.md":{"words":{"initial":70,"current":99},"characters":{"initial":222,"current":509},"sentences":{"initial":1,"current":1},"footnotes":{"initial":0,"current":0},"citations":{"initial":0,"current":0},"pages":{"initial":0.2,"current":0.3}},"100-UTTU人物合辑/神秘学家｜Arcanist/星锑.md":{"words":{"initial":420,"current":420},"characters":{"initial":793,"current":793},"sentences":{"initial":1,"current":1},"footnotes":{"initial":0,"current":0},"citations":{"initial":0,"current":0},"pages":{"initial":1.4,"current":1.4}}}}