{
  "biggerIcons": "mobile",
  "clickableIcons": "desktop",
  "showAllFileIcons": false,
  "showItemName": "desktop",
  "biggerSearchResults": "mobile",
  "maxSearchResults": 50,
  "colorPicker1": "list",
  "colorPicker2": "rgb",
  "uncolorHover": false,
  "uncolorSelect": false,
  "rememberDeletedItems": false,
  "appIcons": {},
  "tabIcons": {
    "quiet-outline": {
      "icon": "lucide-list-tree"
    }
  },
  "fileIcons": {
    "100-UTTU人物合辑": {
      "icon": "lucide-person-standing"
    }
  },
  "groupIcons": {},
  "propertyIcons": {},
  "ribbonIcons": {}
}